matomo_driver/__init__.py
matomo_driver/client.py
matomo_driver/logic.py
matomo_driver/serializers.py
hirmeos_matomo_driver-0.0.2.dist-info/LICENSE
hirmeos_matomo_driver-0.0.2.dist-info/METADATA
hirmeos_matomo_driver-0.0.2.dist-info/WHEEL
hirmeos_matomo_driver-0.0.2.dist-info/top_level.txt
hirmeos_matomo_driver-0.0.2.dist-info/RECORD
