Metadata-Version: 2.1
Name: hirmeos-matomo-driver
Version: 0.0.2
Summary: Functions required by the matomo-driver
Author-email: Tai Jantarungsee <tai.jantarungsee@ubiquitypress.com>
Classifier: Programming Language :: Python :: 3
Classifier: License :: OSI Approved :: MIT License
Classifier: Operating System :: OS Independent
Requires-Python: >=3.10
License-File: LICENSE
Requires-Dist: requests >=2.25
Requires-Dist: pydantic >=2.0
